ortoolpy/__init__.py
ortoolpy/cover_by_rect.py
ortoolpy/etc.py
ortoolpy/py.typed
ortoolpy/optimization/__init__.py
ortoolpy-0.9.0.dist-info/METADATA
ortoolpy-0.9.0.dist-info/WHEEL
ortoolpy-0.9.0.dist-info/licenses/LICENSE
ortoolpy-0.9.0.dist-info/RECORD
