Metadata-Version: 2.4
Name: ortoolpy
Version: 0.9.0
Summary: `ortoolpy` is a package for Operations Research.
Project-URL: homepage, https://github.com/SaitoTsutomu/ortoolpy
Author-email: Saito Tsutomu <tsutomu7@hotmail.co.jp>
License: Apache-2.0
License-File: LICENSE
Classifier: Development Status :: 1 - Planning
Classifier: Intended Audience :: Developers
Classifier: Intended Audience :: Science/Research
Classifier: License :: OSI Approved :: Apache Software License
Classifier: Programming Language :: Python
Classifier: Topic :: Scientific/Engineering
Classifier: Topic :: Software Development
Requires-Python: >=3.12
Requires-Dist: more-itertools>=10.7.0
Requires-Dist: pandas>=2.3.0
Requires-Dist: pulp>=3.2.1
